main.py
myexerc-0.1.0.dist-info/METADATA
myexerc-0.1.0.dist-info/WHEEL
myexerc-0.1.0.dist-info/entry_points.txt
myexerc-0.1.0.dist-info/top_level.txt
myexerc-0.1.0.dist-info/RECORD
