Metadata-Version: 2.1
Name: myexerc
Version: 0.1.0
Summary: UNKNOWN
Home-page: UNKNOWN
Author: Patchu
License: UNKNOWN
Platform: UNKNOWN
Requires-Dist: Click
